setup.py
crm/__init__.py
crm/load.py
crm/models.py
crm4j.egg-info/PKG-INFO
crm4j.egg-info/SOURCES.txt
crm4j.egg-info/dependency_links.txt
crm4j.egg-info/requires.txt
crm4j.egg-info/top_level.txt