Metadata-Version: 1.0
Name: crm4j
Version: 0.1
Summary: Meta-implementation of the CIDOC-CRM for Neo4j, using neomodel
Home-page: UNKNOWN
Author: Erick Peirson
Author-email: erick.peirson@gmail.com
License: GNU GPL 3
Platform: UNKNOWN
